LICENSE
MANIFEST.in
README.md
README.rst
setup.py
SimpleHttpFetch/__init__.py
SimpleHttpFetch.egg-info/PKG-INFO
SimpleHttpFetch.egg-info/SOURCES.txt
SimpleHttpFetch.egg-info/dependency_links.txt
SimpleHttpFetch.egg-info/top_level.txt
doc/SimpleHttpFetch.html
doc/exceptions.html