Metadata-Version: 1.1
Name: SimpleHttpFetch
Version: 2.0.0
Summary: Python module that will, in a single line, fetch an http/https url and return a string or dictionary (JSON)
Home-page: https://github.com/kata198/SimpleHttpFetch
Author: Tim Savannah
Author-email: kata198@gmail.com
License: LGPLv2
Keywords: fetch,url,GET,http,html,https,string,json,dict,as,simple,easy,basic,request,method,str,fetchUrl,fetchUrlAsJson,redirect
Platform: UNKNOWN
Classifier: Development Status :: 5 - Production/Stable
Classifier: Programming Language :: Python
Classifier: License :: OSI Approved :: GNU Lesser General Public License v2 (LGPLv2)
Classifier: Programming Language :: Python :: 2
Classifier: Programming Language :: Python :: 2
Classifier: Programming Language :: Python :: 2.6
Classifier: Programming Language :: Python :: 2.7
Classifier: Programming Language :: Python :: 3
Classifier: Programming Language :: Python :: 3.3
Classifier: Programming Language :: Python :: 3.4
Classifier: Topic :: Internet :: WWW/HTTP
Classifier: Topic :: Text Processing :: Markup :: HTML
Classifier: Topic :: Software Development :: Libraries :: Python Modules
